DENOLIB_D18/__init__.py
DENOLIB_D18-0.1.4.dist-info/METADATA
DENOLIB_D18-0.1.4.dist-info/WHEEL
DENOLIB_D18-0.1.4.dist-info/top_level.txt
DENOLIB_D18-0.1.4.dist-info/RECORD
