Metadata-Version: 2.1
Name: DENOLIB_D18
Version: 0.1.4
Summary: Thư Viện Về Python Cơ Bản
Author: DENO
Author-email: vinhytb3010@gmail.com
Classifier: Programming Language :: Python :: 3
Classifier: License :: OSI Approved :: MIT License
Classifier: Operating System :: OS Independent
